{
  "updated_at": "2026-07-23T14:55:11.018019+05:30",
  "file_count": 99,
  "hubs": [],
  "importers": {},
  "imports": {},
  "recent_events": [
    {
      "time": "2026-07-23T13:34:29.603672+05:30",
      "op": "CREATE",
      "path": "frontend/src/app/TeacherApp.tsx",
      "lang": "typescript",
      "lines": 1081,
      "delta": 1081,
      "size_delta": 51139,
      "dirty": true
    },
    {
      "time": "2026-07-23T13:34:40.228081+05:30",
      "op": "REMOVE",
      "path": "frontend/src/app/TeacherApp.tsx",
      "lang": "typescript",
      "delta": -1081,
      "size_delta": -51139
    },
    {
      "time": "2026-07-23T13:34:40.229063+05:30",
      "op": "CREATE",
      "path": "frontend/src/app/TeacherApp.tsx",
      "lang": "typescript",
      "lines": 1081,
      "delta": 1081,
      "size_delta": 51135,
      "dirty": true
    },
    {
      "time": "2026-07-23T13:34:45.715533+05:30",
      "op": "REMOVE",
      "path": "frontend/src/app/TeacherApp.tsx",
      "lang": "typescript",
      "delta": -1081,
      "size_delta": -51135
    },
    {
      "time": "2026-07-23T13:34:45.719943+05:30",
      "op": "CREATE",
      "path": "frontend/src/app/TeacherApp.tsx",
      "lang": "typescript",
      "lines": 1081,
      "delta": 1081,
      "size_delta": 51115,
      "dirty": true
    },
    {
      "time": "2026-07-23T14:25:48.481144+05:30",
      "op": "REMOVE",
      "path": "backend/src/routes/parent.ts",
      "lang": "typescript",
      "delta": -370,
      "size_delta": -11473
    },
    {
      "time": "2026-07-23T14:25:48.484314+05:30",
      "op": "CREATE",
      "path": "backend/src/routes/parent.ts",
      "lang": "typescript",
      "lines": 395,
      "delta": 395,
      "size_delta": 12149,
      "dirty": true
    },
    {
      "time": "2026-07-23T14:26:04.890896+05:30",
      "op": "CREATE",
      "path": "frontend/src/api/parent.ts",
      "lang": "typescript",
      "lines": 85,
      "delta": 85,
      "size_delta": 2378
    },
    {
      "time": "2026-07-23T14:26:18.771271+05:30",
      "op": "CREATE",
      "path": "frontend/src/lib/date.ts",
      "lang": "typescript",
      "lines": 35,
      "delta": 35,
      "size_delta": 1240
    },
    {
      "time": "2026-07-23T14:26:26.335338+05:30",
      "op": "CREATE",
      "path": "frontend/src/lib/diaryDone.ts",
      "lang": "typescript",
      "lines": 38,
      "delta": 38,
      "size_delta": 1064
    },
    {
      "time": "2026-07-23T14:29:07.179446+05:30",
      "op": "REMOVE",
      "path": "frontend/src/app/ParentApp.tsx",
      "lang": "typescript",
      "delta": -472,
      "size_delta": -23010
    },
    {
      "time": "2026-07-23T14:29:07.195091+05:30",
      "op": "CREATE",
      "path": "frontend/src/app/ParentApp.tsx",
      "lang": "typescript",
      "lines": 711,
      "delta": 711,
      "size_delta": 33678,
      "dirty": true
    },
    {
      "time": "2026-07-23T14:29:15.289385+05:30",
      "op": "REMOVE",
      "path": "frontend/src/app/ParentApp.tsx",
      "lang": "typescript",
      "delta": -711,
      "size_delta": -33678
    },
    {
      "time": "2026-07-23T14:29:15.290573+05:30",
      "op": "CREATE",
      "path": "frontend/src/app/ParentApp.tsx",
      "lang": "typescript",
      "lines": 711,
      "delta": 711,
      "size_delta": 33699,
      "dirty": true
    },
    {
      "time": "2026-07-23T14:29:19.610035+05:30",
      "op": "REMOVE",
      "path": "frontend/src/app/ParentApp.tsx",
      "lang": "typescript",
      "delta": -711,
      "size_delta": -33699
    },
    {
      "time": "2026-07-23T14:29:19.620411+05:30",
      "op": "CREATE",
      "path": "frontend/src/app/ParentApp.tsx",
      "lang": "typescript",
      "lines": 711,
      "delta": 711,
      "size_delta": 33675,
      "dirty": true
    },
    {
      "time": "2026-07-23T14:29:47.234191+05:30",
      "op": "REMOVE",
      "path": "frontend/src/app/ParentApp.tsx",
      "lang": "typescript",
      "delta": -711,
      "size_delta": -33675
    },
    {
      "time": "2026-07-23T14:29:47.242061+05:30",
      "op": "CREATE",
      "path": "frontend/src/app/ParentApp.tsx",
      "lang": "typescript",
      "lines": 711,
      "delta": 711,
      "size_delta": 33665,
      "dirty": true
    },
    {
      "time": "2026-07-23T14:29:59.969365+05:30",
      "op": "REMOVE",
      "path": "frontend/src/app/ParentApp.tsx",
      "lang": "typescript",
      "delta": -711,
      "size_delta": -33665
    },
    {
      "time": "2026-07-23T14:29:59.97676+05:30",
      "op": "CREATE",
      "path": "frontend/src/app/ParentApp.tsx",
      "lang": "typescript",
      "lines": 705,
      "delta": 705,
      "size_delta": 33492,
      "dirty": true
    },
    {
      "time": "2026-07-23T14:47:06.77042+05:30",
      "op": "REMOVE",
      "path": "frontend/src/api/parent.ts",
      "lang": "typescript",
      "delta": -85,
      "size_delta": -2378
    },
    {
      "time": "2026-07-23T14:47:06.778879+05:30",
      "op": "CREATE",
      "path": "frontend/src/api/parent.ts",
      "lang": "typescript",
      "lines": 98,
      "delta": 98,
      "size_delta": 2689,
      "dirty": true
    },
    {
      "time": "2026-07-23T14:47:19.300134+05:30",
      "op": "REMOVE",
      "path": "frontend/src/app/ParentApp.tsx",
      "lang": "typescript",
      "delta": -705,
      "size_delta": -33492
    },
    {
      "time": "2026-07-23T14:47:19.301644+05:30",
      "op": "CREATE",
      "path": "frontend/src/app/ParentApp.tsx",
      "lang": "typescript",
      "lines": 718,
      "delta": 718,
      "size_delta": 33935,
      "dirty": true
    },
    {
      "time": "2026-07-23T14:47:26.123686+05:30",
      "op": "REMOVE",
      "path": "frontend/src/app/ParentApp.tsx",
      "lang": "typescript",
      "delta": -718,
      "size_delta": -33935
    },
    {
      "time": "2026-07-23T14:47:26.133809+05:30",
      "op": "CREATE",
      "path": "frontend/src/app/ParentApp.tsx",
      "lang": "typescript",
      "lines": 728,
      "delta": 728,
      "size_delta": 34247,
      "dirty": true
    },
    {
      "time": "2026-07-23T14:47:31.850407+05:30",
      "op": "REMOVE",
      "path": "frontend/src/app/ParentApp.tsx",
      "lang": "typescript",
      "delta": -728,
      "size_delta": -34247
    },
    {
      "time": "2026-07-23T14:47:31.866794+05:30",
      "op": "CREATE",
      "path": "frontend/src/app/ParentApp.tsx",
      "lang": "typescript",
      "lines": 728,
      "delta": 728,
      "size_delta": 34266,
      "dirty": true
    },
    {
      "time": "2026-07-23T14:52:28.895314+05:30",
      "op": "REMOVE",
      "path": "backend/src/routes/parent.ts",
      "lang": "typescript",
      "delta": -395,
      "size_delta": -12149
    },
    {
      "time": "2026-07-23T14:52:28.896781+05:30",
      "op": "CREATE",
      "path": "backend/src/routes/parent.ts",
      "lang": "typescript",
      "lines": 397,
      "delta": 397,
      "size_delta": 12238,
      "dirty": true
    },
    {
      "time": "2026-07-23T14:52:36.877261+05:30",
      "op": "REMOVE",
      "path": "frontend/src/api/parent.ts",
      "lang": "typescript",
      "delta": -98,
      "size_delta": -2689
    },
    {
      "time": "2026-07-23T14:52:36.878463+05:30",
      "op": "CREATE",
      "path": "frontend/src/api/parent.ts",
      "lang": "typescript",
      "lines": 133,
      "delta": 133,
      "size_delta": 3512,
      "dirty": true
    },
    {
      "time": "2026-07-23T14:53:06.809341+05:30",
      "op": "REMOVE",
      "path": "frontend/src/app/ParentApp.tsx",
      "lang": "typescript",
      "delta": -728,
      "size_delta": -34266
    },
    {
      "time": "2026-07-23T14:53:06.825218+05:30",
      "op": "CREATE",
      "path": "frontend/src/app/ParentApp.tsx",
      "lang": "typescript",
      "lines": 729,
      "delta": 729,
      "size_delta": 34344,
      "dirty": true
    },
    {
      "time": "2026-07-23T14:53:48.416482+05:30",
      "op": "REMOVE",
      "path": "frontend/src/app/ParentApp.tsx",
      "lang": "typescript",
      "delta": -729,
      "size_delta": -34344
    },
    {
      "time": "2026-07-23T14:53:48.421123+05:30",
      "op": "CREATE",
      "path": "frontend/src/app/ParentApp.tsx",
      "lang": "typescript",
      "lines": 764,
      "delta": 764,
      "size_delta": 35566,
      "dirty": true
    },
    {
      "time": "2026-07-23T14:53:58.997614+05:30",
      "op": "REMOVE",
      "path": "frontend/src/app/ParentApp.tsx",
      "lang": "typescript",
      "delta": -764,
      "size_delta": -35566
    },
    {
      "time": "2026-07-23T14:53:59.020577+05:30",
      "op": "CREATE",
      "path": "frontend/src/app/ParentApp.tsx",
      "lang": "typescript",
      "lines": 784,
      "delta": 784,
      "size_delta": 36195,
      "dirty": true
    },
    {
      "time": "2026-07-23T14:54:06.928098+05:30",
      "op": "REMOVE",
      "path": "frontend/src/app/ParentApp.tsx",
      "lang": "typescript",
      "delta": -784,
      "size_delta": -36195
    },
    {
      "time": "2026-07-23T14:54:06.92965+05:30",
      "op": "CREATE",
      "path": "frontend/src/app/ParentApp.tsx",
      "lang": "typescript",
      "lines": 782,
      "delta": 782,
      "size_delta": 36118,
      "dirty": true
    },
    {
      "time": "2026-07-23T14:54:17.080646+05:30",
      "op": "REMOVE",
      "path": "frontend/src/app/ParentApp.tsx",
      "lang": "typescript",
      "delta": -782,
      "size_delta": -36118
    },
    {
      "time": "2026-07-23T14:54:17.08182+05:30",
      "op": "CREATE",
      "path": "frontend/src/app/ParentApp.tsx",
      "lang": "typescript",
      "lines": 782,
      "delta": 782,
      "size_delta": 36097,
      "dirty": true
    },
    {
      "time": "2026-07-23T14:54:24.168983+05:30",
      "op": "REMOVE",
      "path": "frontend/src/app/ParentApp.tsx",
      "lang": "typescript",
      "delta": -782,
      "size_delta": -36097
    },
    {
      "time": "2026-07-23T14:54:24.176134+05:30",
      "op": "CREATE",
      "path": "frontend/src/app/ParentApp.tsx",
      "lang": "typescript",
      "lines": 782,
      "delta": 782,
      "size_delta": 36056,
      "dirty": true
    },
    {
      "time": "2026-07-23T14:54:33.915131+05:30",
      "op": "REMOVE",
      "path": "frontend/src/app/ParentApp.tsx",
      "lang": "typescript",
      "delta": -782,
      "size_delta": -36056
    },
    {
      "time": "2026-07-23T14:54:33.916463+05:30",
      "op": "CREATE",
      "path": "frontend/src/app/ParentApp.tsx",
      "lang": "typescript",
      "lines": 783,
      "delta": 783,
      "size_delta": 36086,
      "dirty": true
    },
    {
      "time": "2026-07-23T14:54:45.780375+05:30",
      "op": "REMOVE",
      "path": "frontend/src/app/ParentApp.tsx",
      "lang": "typescript",
      "delta": -783,
      "size_delta": -36086
    },
    {
      "time": "2026-07-23T14:54:45.787433+05:30",
      "op": "CREATE",
      "path": "frontend/src/app/ParentApp.tsx",
      "lang": "typescript",
      "lines": 783,
      "delta": 783,
      "size_delta": 36086,
      "dirty": true
    },
    {
      "time": "2026-07-23T14:55:10.980153+05:30",
      "op": "REMOVE",
      "path": "frontend/src/app/ParentApp.tsx",
      "lang": "typescript",
      "delta": -783,
      "size_delta": -36086
    },
    {
      "time": "2026-07-23T14:55:10.99238+05:30",
      "op": "CREATE",
      "path": "frontend/src/app/ParentApp.tsx",
      "lang": "typescript",
      "lines": 807,
      "delta": 807,
      "size_delta": 37257,
      "dirty": true
    }
  ],
  "working_set": {
    "files": {
      "backend/src/routes/admin.ts": {
        "path": "backend/src/routes/admin.ts",
        "first_touch": "2026-07-23T13:07:41.174424+05:30",
        "last_touch": "2026-07-23T13:07:41.174424+05:30",
        "edit_count": 1,
        "net_delta": 1033,
        "is_hub": false,
        "importers": 0
      },
      "backend/src/routes/parent.ts": {
        "path": "backend/src/routes/parent.ts",
        "first_touch": "2026-07-23T14:52:28.929766+05:30",
        "last_touch": "2026-07-23T14:52:28.929766+05:30",
        "edit_count": 1,
        "net_delta": 397,
        "is_hub": false,
        "importers": 0
      },
      "backend/src/routes/teacher.ts": {
        "path": "backend/src/routes/teacher.ts",
        "first_touch": "2026-07-23T13:30:31.878897+05:30",
        "last_touch": "2026-07-23T13:30:31.878897+05:30",
        "edit_count": 1,
        "net_delta": 684,
        "is_hub": false,
        "importers": 0
      },
      "frontend/src/api/admin.ts": {
        "path": "frontend/src/api/admin.ts",
        "first_touch": "2026-07-23T12:19:24.532489+05:30",
        "last_touch": "2026-07-23T12:19:24.532489+05:30",
        "edit_count": 1,
        "net_delta": 383,
        "is_hub": false,
        "importers": 0
      },
      "frontend/src/api/parent.ts": {
        "path": "frontend/src/api/parent.ts",
        "first_touch": "2026-07-23T14:52:36.889022+05:30",
        "last_touch": "2026-07-23T14:52:36.889022+05:30",
        "edit_count": 1,
        "net_delta": 133,
        "is_hub": false,
        "importers": 0
      },
      "frontend/src/api/teacher.ts": {
        "path": "frontend/src/api/teacher.ts",
        "first_touch": "2026-07-23T13:31:00.398025+05:30",
        "last_touch": "2026-07-23T13:31:00.398025+05:30",
        "edit_count": 1,
        "net_delta": 191,
        "is_hub": false,
        "importers": 0
      },
      "frontend/src/app/AdminApp.tsx": {
        "path": "frontend/src/app/AdminApp.tsx",
        "first_touch": "2026-07-23T12:20:09.447133+05:30",
        "last_touch": "2026-07-23T12:20:09.447133+05:30",
        "edit_count": 1,
        "net_delta": 3649,
        "is_hub": false,
        "importers": 0
      },
      "frontend/src/app/ParentApp.tsx": {
        "path": "frontend/src/app/ParentApp.tsx",
        "first_touch": "2026-07-23T14:55:11.014984+05:30",
        "last_touch": "2026-07-23T14:55:11.014984+05:30",
        "edit_count": 1,
        "net_delta": 807,
        "is_hub": false,
        "importers": 0
      },
      "frontend/src/app/SharedScreens.tsx": {
        "path": "frontend/src/app/SharedScreens.tsx",
        "first_touch": "2026-07-23T13:00:28.949175+05:30",
        "last_touch": "2026-07-23T13:00:28.949175+05:30",
        "edit_count": 1,
        "net_delta": 294,
        "is_hub": false,
        "importers": 0
      },
      "frontend/src/app/TeacherApp.tsx": {
        "path": "frontend/src/app/TeacherApp.tsx",
        "first_touch": "2026-07-23T13:34:45.738649+05:30",
        "last_touch": "2026-07-23T13:34:45.738649+05:30",
        "edit_count": 1,
        "net_delta": 1081,
        "is_hub": false,
        "importers": 0
      },
      "frontend/src/lib/date.ts": {
        "path": "frontend/src/lib/date.ts",
        "first_touch": "2026-07-23T14:26:18.781125+05:30",
        "last_touch": "2026-07-23T14:26:18.781125+05:30",
        "edit_count": 1,
        "net_delta": 35,
        "is_hub": false,
        "importers": 0
      },
      "frontend/src/lib/diaryDone.ts": {
        "path": "frontend/src/lib/diaryDone.ts",
        "first_touch": "2026-07-23T14:26:26.343583+05:30",
        "last_touch": "2026-07-23T14:26:26.343583+05:30",
        "edit_count": 1,
        "net_delta": 38,
        "is_hub": false,
        "importers": 0
      }
    },
    "started_at": "2026-07-23T12:06:33.024111+05:30"
  }
}
}